books/__init__.py
books/api/Api.py
books/api/BankAccountsApi.py
books/api/BankRulesApi.py
books/api/BankTransactionsApi.py
books/api/BaseCurrencyAdjustmentApi.py
books/api/BillsApi.py
books/api/ChartOfAccountsApi.py
books/api/ContactPersonsApi.py
books/api/ContactsApi.py
books/api/CreditNotesApi.py
books/api/CustomerPaymentsApi.py
books/api/EstimatesApi.py
books/api/ExpensesApi.py
books/api/InvoicesApi.py
books/api/ItemsApi.py
books/api/JournalsApi.py
books/api/OrganizationsApi.py
books/api/ProjectsApi.py
books/api/RecurringExpensesApi.py
books/api/RecurringInvoicesApi.py
books/api/SettingsApi.py
books/api/UsersApi.py
books/api/VendorPaymentsApi.py
books/api/__init__.py
books/exception/BooksException.py
books/exception/__init__.py
books/model/Account.py
books/model/Address.py
books/model/AddressFormat.py
books/model/AutoReminderList.py
books/model/Autoreminder.py
books/model/BankAccount.py
books/model/BankAccountList.py
books/model/BankRule.py
books/model/BankRuleList.py
books/model/BaseCurrencyAdjustment.py
books/model/BaseCurrencyAdjustmentList.py
books/model/Bill.py
books/model/BillList.py
books/model/BillPayment.py
books/model/ChartOfAccount.py
books/model/ChartOfAccountList.py
books/model/Comment.py
books/model/CommentList.py
books/model/Contact.py
books/model/ContactList.py
books/model/ContactPerson.py
books/model/ContactPersonList.py
books/model/CreditNote.py
books/model/CreditNoteList.py
books/model/CreditNoteRefund.py
books/model/CreditNoteRefundList.py
books/model/CreditnoteSetting.py
books/model/Criteria.py
books/model/Currency.py
books/model/CurrencyList.py
books/model/CustomField.py
books/model/Customer.py
books/model/CustomerPayment.py
books/model/CustomerPaymentList.py
books/model/DefaultTemplate.py
books/model/Email.py
books/model/EmailHistory.py
books/model/EmailId.py
books/model/EmailTemplate.py
books/model/Estimate.py
books/model/EstimateList.py
books/model/EstimateSetting.py
books/model/ExchangeRate.py
books/model/ExchangeRateList.py
zohobooks_api-1.4.dist-info/LICENSE
zohobooks_api-1.4.dist-info/METADATA
zohobooks_api-1.4.dist-info/WHEEL
zohobooks_api-1.4.dist-info/top_level.txt
zohobooks_api-1.4.dist-info/RECORD
