Metadata-Version: 2.1
Name: zohobooks-api
Version: 1.4
Summary: Zoho Books Python Client Library
Home-page: UNKNOWN
Author: Sagar
Author-email: sagarnrng17@gmail.com
License: MIT
Platform: UNKNOWN
